trapeza/__init__.py
trapeza/_version.py
trapeza/context.py
trapeza/exception.py
trapeza/metric.py
trapeza/utils.py
trapeza/__cache__/README.md
trapeza/account/__init__.py
trapeza/account/base_account.py
trapeza/account/execution_heap.cp37-win_amd64.pyd
trapeza/account/execution_heap.cpp
trapeza/account/execution_heap.pxd
trapeza/account/execution_heap.pyx
trapeza/account/fx_account.cp37-win_amd64.pyd
trapeza/account/fx_account.cpp
trapeza/account/fx_account.pxd
trapeza/account/fx_account.pyx
trapeza/account/order_management.py
trapeza/arithmetics/__init__.py
trapeza/arithmetics/arithmetics.c
trapeza/arithmetics/arithmetics.cp37-win_amd64.pyd
trapeza/arithmetics/arithmetics.pxd
trapeza/arithmetics/arithmetics.pyx
trapeza/arithmetics/cdecimal.c
trapeza/arithmetics/cdecimal.cp37-win_amd64.pyd
trapeza/arithmetics/cdecimal.pxd
trapeza/arithmetics/cdecimal.pyx
trapeza/arithmetics/cfloat.c
trapeza/arithmetics/cfloat.cp37-win_amd64.pyd
trapeza/arithmetics/cfloat.pxd
trapeza/arithmetics/cfloat.pyx
trapeza/arithmetics/dtoa.c
trapeza/arithmetics/dtoa.cp37-win_amd64.pyd
trapeza/arithmetics/dtoa.pxd
trapeza/arithmetics/dtoa.pyx
trapeza/arithmetics/libmpdec.c
trapeza/arithmetics/libmpdec.cp37-win_amd64.pyd
trapeza/arithmetics/libmpdec.pxd
trapeza/arithmetics/libmpdec.pyx
trapeza/dashboard/__init__.py
trapeza/dashboard/base_dashboard.py
trapeza/dashboard/fx_dashboard.py
trapeza/engine/__init__.py
trapeza/engine/base_engine.py
trapeza/engine/fx_engine.py
trapeza/profiling/__init__.py
trapeza/profiling/mem_profile_acc.py
trapeza/profiling/mem_profile_libmpdec.py
trapeza/profiling/mem_profile_py_dtoa_ryu.py
trapeza/profiling/profile_FXAccount_c_total_balance.py
trapeza/profiling/profile_FXEngine_run.py
trapeza/profiling/profile_add.py
trapeza/profiling/profile_dtoa.py
trapeza/profiling/profile_lines_FXEngine_run.py
trapeza/src/__init__.py
trapeza/src/linux/__init__.py
trapeza/src/win/__init__.py
trapeza/src/win/mpdecimal-2.5.1/libmpdec/libmpdec-2.5.1.dll
trapeza/strategy/__init__.py
trapeza-0.0.11.dist-info/LICENSE.txt
trapeza-0.0.11.dist-info/METADATA
trapeza-0.0.11.dist-info/WHEEL
trapeza-0.0.11.dist-info/top_level.txt
trapeza-0.0.11.dist-info/RECORD
