Metadata-Version: 2.1
Name: trapeza
Version: 0.0.11
Summary: Backtesting and Simulation package for financial transactions and trading
Home-page: https://gitlab.com/LHuebser/trapeza.git
Author: Louis Huebser
License: MIT
Platform: any
Classifier: Development Status :: 4 - Beta
Classifier: License :: OSI Approved :: MIT License
Classifier: Intended Audience :: Financial and Insurance Industry
Classifier: Intended Audience :: Science/Research
Classifier: Topic :: Scientific/Engineering
Classifier: Topic :: Scientific/Engineering :: Mathematics
Classifier: Topic :: Office/Business :: Financial :: Investment
Classifier: Operating System :: OS Independent
Classifier: Programming Language :: C
Classifier: Programming Language :: C++
Classifier: Programming Language :: Python :: 3
Classifier: Programming Language :: Python :: 3 :: Only
Classifier: Programming Language :: Python :: Implementation :: CPython
Requires-Dist: numpy
Requires-Dist: pandas
Requires-Dist: scipy
Requires-Dist: joblib
Requires-Dist: scikit-learn
Requires-Dist: dash
Requires-Dist: plotly
Requires-Dist: matplotlib
Requires-Dist: flask
Requires-Dist: setuptools
Requires-Dist: pathlib ; python_version < "3.4"
